oddsmaker/__init__.py
oddsmaker/state_space.py
oddsmaker-0.1.1.dist-info/LICENSE
oddsmaker-0.1.1.dist-info/METADATA
oddsmaker-0.1.1.dist-info/WHEEL
oddsmaker-0.1.1.dist-info/top_level.txt
oddsmaker-0.1.1.dist-info/RECORD
