Metadata-Version: 2.1
Name: oddsmaker
Version: 0.1.1
Summary: Speedy Implementation of Team and Player Rating Algorithms
Home-page: https://github.com/btatkinson/moneyball
Author: Blake Atkinson
Author-email: blaketatkinson@gmail.com
License: MIT License
License-File: LICENSE
Requires-Dist: numpy
Requires-Dist: pandas
